bardic/__init__.py
bardic/cli/__init__.py
bardic/cli/bundler.py
bardic/cli/graph.py
bardic/cli/main.py
bardic/compiler/__init__.py
bardic/compiler/compiler.py
bardic/compiler/parser.py
bardic/compiler/parsing/__init__.py
bardic/compiler/parsing/blocks.py
bardic/compiler/parsing/content.py
bardic/compiler/parsing/core.py
bardic/compiler/parsing/directives.py
bardic/compiler/parsing/errors.py
bardic/compiler/parsing/indentation.py
bardic/compiler/parsing/io.py
bardic/compiler/parsing/preprocessing.py
bardic/compiler/parsing/validation.py
bardic/runtime/__init__.py
bardic/runtime/engine.py
bardic/stdlib/__init__.py
bardic/stdlib/dice.py
bardic/stdlib/economy.py
bardic/stdlib/inventory.py
bardic/stdlib/relationship.py
bardic/templates/browser/engine_browser.py
bardic/templates/browser/index.html
bardic/templates/browser/player.py
bardic/templates/browser/style.css
bardic/templates/browser/pyodide/attrs-25.2.0-py3-none-any.whl
bardic/templates/browser/pyodide/jinja2-3.1.6-py3-none-any.whl
bardic/templates/browser/pyodide/markupsafe-3.0.2-cp313-cp313-pyodide_2025_0_wasm32.whl
bardic/templates/browser/pyodide/micropip-0.11.0-py3-none-any.whl
bardic/templates/browser/pyodide/more_itertools-10.6.0-py3-none-any.whl
bardic/templates/browser/pyodide/networkx-3.4.2-py3-none-any.whl
bardic/templates/browser/pyodide/nltk-3.9.1-py3-none-any.whl
bardic/templates/browser/pyodide/numpy-2.2.5-cp313-cp313-pyodide_2025_0_wasm32.whl
bardic/templates/browser/pyodide/pillow-11.3.0-cp313-cp313-pyodide_2025_0_wasm32.whl
bardic/templates/browser/pyodide/pygments-2.19.1-py3-none-any.whl
bardic/templates/browser/pyodide/pyodide-lock.json
bardic/templates/browser/pyodide/pyodide.asm.js
bardic/templates/browser/pyodide/pyodide.asm.wasm
bardic/templates/browser/pyodide/pyodide.js
bardic/templates/browser/pyodide/pyodide.mjs
bardic/templates/browser/pyodide/python_dateutil-2.9.0.post0-py2.py3-none-any.whl
bardic/templates/browser/pyodide/python_stdlib.zip
bardic-0.6.1.dist-info/licenses/LICENSE
bardic-0.6.1.dist-info/METADATA
bardic-0.6.1.dist-info/WHEEL
bardic-0.6.1.dist-info/entry_points.txt
bardic-0.6.1.dist-info/top_level.txt
bardic-0.6.1.dist-info/RECORD
