Metadata-Version: 2.4
Name: bardic
Version: 0.6.1
Summary: Python-first interactive fiction engine
Author-email: Kate Louie <katehlouie@gmail.com>
License: MIT
Project-URL: Homepage, https://github.com/katelouie/bardic
Project-URL: Issues, https://github.com/katelouie/bardic/issues
Project-URL: Documentation, https://github.com/katelouie/bardic/blob/main/docs/spec.md
Keywords: interactive fiction,if,dsl,narrative,gamedev,ink,twine
Classifier: Development Status :: 3 - Alpha
Classifier: Programming Language :: Python :: 3
Classifier: Programming Language :: Python :: 3.8
Classifier: Programming Language :: Python :: 3.9
Classifier: Programming Language :: Python :: 3.10
Classifier: Programming Language :: Python :: 3.11
Classifier: Programming Language :: Python :: 3.12
Classifier: License :: OSI Approved :: MIT License
Classifier: Operating System :: OS Independent
Classifier: Topic :: Games/Entertainment
Classifier: Topic :: Software Development :: Libraries :: Application Frameworks
Classifier: Topic :: Text Processing :: Markup
Requires-Python: >=3.8
License-File: LICENSE
Requires-Dist: click>=8.0
Requires-Dist: graphviz
Provides-Extra: nicegui
Requires-Dist: nicegui; extra == "nicegui"
Requires-Dist: markdown; extra == "nicegui"
Provides-Extra: web
Requires-Dist: fastapi; extra == "web"
Requires-Dist: uvicorn[standard]; extra == "web"
Provides-Extra: reflex
Requires-Dist: reflex; extra == "reflex"
Requires-Dist: markdown; extra == "reflex"
Provides-Extra: dev
Requires-Dist: black; extra == "dev"
Requires-Dist: ruff; extra == "dev"
Requires-Dist: mypy; extra == "dev"
Requires-Dist: pytest; extra == "dev"
Requires-Dist: pytest-cov; extra == "dev"
Dynamic: license-file
